Workbook

Sheet Dashboard
B2: Group-Level Business Performance MIS Dashboard
B3: Consolidated view across verticals | FY25-FY26 (8 quarters) | All figures in INR Crores
B5: Total Revenue (Latest Qtr) | E5: Total Cost (Latest Qtr) | H5: Group EBITDA Margin % | K5: YoY Revenue Growth %
B6: =SUMIFS('Raw Data'!C:C,'Raw Data'!A:A,"Q4 FY26") -> 17040.3 | E6: =SUMIFS('Raw Data'!D:D,'Raw Data'!A:A,"Q4 FY26") -> 10385.2 | H6: =(B6-E6)/B6 -> 0.39055064 | K6: =(B6-SUMIFS('Raw Data'!C:C,'Raw Data'!A:A,"Q4 FY25"))/SUMIFS('Raw Data'!C:C,'Raw Data'!A:A,"Q4 FY25") -> 0.065245115
B9: Revenue by Vertical — Latest Quarter vs Budget
B10: Vertical | C10: Actual Revenue (Cr) | D10: Budget Revenue (Cr) | E10: Variance (Cr) | F10: Variance %
B11: Ports & Logistics | C11: =SUMIFS('Raw Data'!C:C,'Raw Data'!A:A,"Q4 FY26",'Raw Data'!B:B,B11) -> 4868.7 | D11: =SUMIFS('Raw Data'!E:E,'Raw Data'!A:A,"Q4 FY26",'Raw Data'!B:B,B11) -> 4981.8 | E11: =C11-D11 -> -113.1 | F11: =E11/D11 -> -0.022702638
B12: Power | C12: =SUMIFS('Raw Data'!C:C,'Raw Data'!A:A,"Q4 FY26",'Raw Data'!B:B,B12) -> 5708.1 | D12: =SUMIFS('Raw Data'!E:E,'Raw Data'!A:A,"Q4 FY26",'Raw Data'!B:B,B12) -> 5681.4 | E12: =C12-D12 -> 26.7 | F12: =E12/D12 -> 0.0046995459
B13: Green Energy | C13: =SUMIFS('Raw Data'!C:C,'Raw Data'!A:A,"Q4 FY26",'Raw Data'!B:B,B13) -> 3136.5 | D13: =SUMIFS('Raw Data'!E:E,'Raw Data'!A:A,"Q4 FY26",'Raw Data'!B:B,B13) -> 3036.5 | E13: =C13-D13 -> 100 | F13: =E13/D13 -> 0.032932653
B14: Cement | C14: =SUMIFS('Raw Data'!C:C,'Raw Data'!A:A,"Q4 FY26",'Raw Data'!B:B,B14) -> 3327 | D14: =SUMIFS('Raw Data'!E:E,'Raw Data'!A:A,"Q4 FY26",'Raw Data'!B:B,B14) -> 3366.5 | E14: =C14-D14 -> -39.5 | F14: =E14/D14 -> -0.011733254
B15: Group Total | C15: =SUM(C11:C14) -> 17040.3 | D15: =SUM(D11:D14) -> 17066.2 | E15: =C15-D15 -> -25.9 | F15: =E15/D15 -> -0.0015176196
B17: Revenue Trend by Vertical (Cr) — All Quarters
B18: Quarter | C18: Ports & Logistics | D18: Power | E18: Green Energy | F18: Cement
B19: Q1 FY25 | C19: =SUMIFS('Raw Data'!C:C,'Raw Data'!A:A,B19,'Raw Data'!B:B,"Ports & Logistics") -> 4108.1 | D19: =SUMIFS('Raw Data'!C:C,'Raw Data'!A:A,B19,'Raw Data'!B:B,"Power") -> 4957.8 | E19: =SUMIFS('Raw Data'!C:C,'Raw Data'!A:A,B19,'Raw Data'!B:B,"Green Energy") -> 2573.9 | F19: =SUMIFS('Raw Data'!C:C,'Raw Data'!A:A,B19,'Raw Data'!B:B,"Cement") -> 3096.5
B20: Q2 FY25 | C20: =SUMIFS('Raw Data'!C:C,'Raw Data'!A:A,B20,'Raw Data'!B:B,"Ports & Logistics") -> 4393.7 | D20: =SUMIFS('Raw Data'!C:C,'Raw Data'!A:A,B20,'Raw Data'!B:B,"Power") -> 5331.3 | E20: =SUMIFS('Raw Data'!C:C,'Raw Data'!A:A,B20,'Raw Data'!B:B,"Green Energy") -> 2668.5 | F20: =SUMIFS('Raw Data'!C:C,'Raw Data'!A:A,B20,'Raw Data'!B:B,"Cement") -> 3092.3
B21: Q3 FY25 | C21: =SUMIFS('Raw Data'!C:C,'Raw Data'!A:A,B21,'Raw Data'!B:B,"Ports & Logistics") -> 4232.2 | D21: =SUMIFS('Raw Data'!C:C,'Raw Data'!A:A,B21,'Raw Data'!B:B,"Power") -> 5162.2 | E21: =SUMIFS('Raw Data'!C:C,'Raw Data'!A:A,B21,'Raw Data'!B:B,"Green Energy") -> 2725.1 | F21: =SUMIFS('Raw Data'!C:C,'Raw Data'!A:A,B21,'Raw Data'!B:B,"Cement") -> 3071.6
B22: Q4 FY25 | C22: =SUMIFS('Raw Data'!C:C,'Raw Data'!A:A,B22,'Raw Data'!B:B,"Ports & Logistics") -> 4431 | D22: =SUMIFS('Raw Data'!C:C,'Raw Data'!A:A,B22,'Raw Data'!B:B,"Power") -> 5298.7 | E22: =SUMIFS('Raw Data'!C:C,'Raw Data'!A:A,B22,'Raw Data'!B:B,"Green Energy") -> 2947.4 | F22: =SUMIFS('Raw Data'!C:C,'Raw Data'!A:A,B22,'Raw Data'!B:B,"Cement") -> 3319.5
B23: Q1 FY26 | C23: =SUMIFS('Raw Data'!C:C,'Raw Data'!A:A,B23,'Raw Data'!B:B,"Ports & Logistics") -> 4189 | D23: =SUMIFS('Raw Data'!C:C,'Raw Data'!A:A,B23,'Raw Data'!B:B,"Power") -> 5087.8 | E23: =SUMIFS('Raw Data'!C:C,'Raw Data'!A:A,B23,'Raw Data'!B:B,"Green Energy") -> 2713.2 | F23: =SUMIFS('Raw Data'!C:C,'Raw Data'!A:A,B23,'Raw Data'!B:B,"Cement") -> 3098.3
B24: Q2 FY26 | C24: =SUMIFS('Raw Data'!C:C,'Raw Data'!A:A,B24,'Raw Data'!B:B,"Ports & Logistics") -> 4613.6 | D24: =SUMIFS('Raw Data'!C:C,'Raw Data'!A:A,B24,'Raw Data'!B:B,"Power") -> 5258.8 | E24: =SUMIFS('Raw Data'!C:C,'Raw Data'!A:A,B24,'Raw Data'!B:B,"Green Energy") -> 2874.9 | F24: =SUMIFS('Raw Data'!C:C,'Raw Data'!A:A,B24,'Raw Data'!B:B,"Cement") -> 3242.7
B25: Q3 FY26 | C25: =SUMIFS('Raw Data'!C:C,'Raw Data'!A:A,B25,'Raw Data'!B:B,"Ports & Logistics") -> 4568.7 | D25: =SUMIFS('Raw Data'!C:C,'Raw Data'!A:A,B25,'Raw Data'!B:B,"Power") -> 5099.7 | E25: =SUMIFS('Raw Data'!C:C,'Raw Data'!A:A,B25,'Raw Data'!B:B,"Green Energy") -> 2786.3 | F25: =SUMIFS('Raw Data'!C:C,'Raw Data'!A:A,B25,'Raw Data'!B:B,"Cement") -> 3260.3
B26: Q4 FY26 | C26: =SUMIFS('Raw Data'!C:C,'Raw Data'!A:A,B26,'Raw Data'!B:B,"Ports & Logistics") -> 4868.7 | D26: =SUMIFS('Raw Data'!C:C,'Raw Data'!A:A,B26,'Raw Data'!B:B,"Power") -> 5708.1 | E26: =SUMIFS('Raw Data'!C:C,'Raw Data'!A:A,B26,'Raw Data'!B:B,"Green Energy") -> 3136.5 | F26: =SUMIFS('Raw Data'!C:C,'Raw Data'!A:A,B26,'Raw Data'!B:B,"Cement") -> 3327

Sheet Data Dictionary
A1: Group-Level Business Performance MIS Dashboard
A2: Data Dictionary & Project Notes
A4: Field | B4: Description | C4: Notes / Source
A5: Quarter | B5: Fiscal quarter (Apr-Mar Indian FY), e.g. Q1 FY25 | C5: FY25 = Apr 2024-Mar 2025
A6: Vertical | B6: Business vertical: Ports & Logistics, Power, Green Energy, Cement | C6: Simulated to mirror Adani Group's core listed entities
A7: Revenue (Cr) | B7: Quarterly revenue in INR Crores | C7: Simulated dataset for portfolio purposes
A8: Cost (Cr) | B8: Quarterly operating cost in INR Crores | C8: Simulated dataset for portfolio purposes
A9: Budget Revenue (Cr) | B9: Board-approved budgeted revenue for the quarter | C9: Simulated dataset for portfolio purposes
A10: Volume (Units) | B10: Operational volume metric — cargo MMT for Ports, MW generated for Power/Green Energy, tonnes for Cement | C10: Unit varies by vertical, see Raw Data notes
A11: EBITDA Margin % | B11: EBITDA as % of revenue for the quarter | C11: Formula: (Revenue minus Cost), divided by Revenue
A13: Project Purpose
A14: This dashboard simulates a centralized, group-level MIS reporting function of the kind used at a diversified infrastructure conglomerate HQ — consolidating quarterly performance across multiple business verticals into a single leadership-facing view, with budget vs actual variance tracking and drill-down by vertical.
A16: Tools Used
A17: Excel (data modeling, formulas, dashboard) — designed for import into Power BI for interactive drill-down
A19: Author
A20: Niyati Ray | linkedin.com/in/niyati-ray | github.com/niyati-ray3

Sheet Raw Data
A1: Quarter | B1: Vertical | C1: Revenue (Cr) | D1: Cost (Cr) | E1: Budget Revenue (Cr) | F1: Volume | G1: Volume Metric | H1: EBITDA Margin %
A2: Q1 FY25 | B2: Ports & Logistics | C2: 4108.1 | D2: 2181.4 | E2: 4082.2 | F2: 91.1 | G2: Cargo Volume (MMT) | H2: =(C2-D2)/C2 -> 0.46900027
A3: Q2 FY25 | B3: Ports & Logistics | C3: 4393.7 | D3: 2447.6 | E3: 4554.8 | F3: 96.4 | G3: Cargo Volume (MMT) | H3: =(C3-D3)/C3 -> 0.44292965
A4: Q3 FY25 | B4: Ports & Logistics | C4: 4232.2 | D4: 2248.1 | E4: 4241.4 | F4: 96.2 | G4: Cargo Volume (MMT) | H4: =(C4-D4)/C4 -> 0.46881055
A5: Q4 FY25 | B5: Ports & Logistics | C5: 4431 | D5: 2383.7 | E5: 4706.4 | F5: 103.3 | G5: Cargo Volume (MMT) | H5: =(C5-D5)/C5 -> 0.46204017
A6: Q1 FY26 | B6: Ports & Logistics | C6: 4189 | D6: 2318.9 | E6: 4451.1 | F6: 94.5 | G6: Cargo Volume (MMT) | H6: =(C6-D6)/C6 -> 0.44643113
A7: Q2 FY26 | B7: Ports & Logistics | C7: 4613.6 | D7: 2574 | E7: 4563.2 | F7: 101.1 | G7: Cargo Volume (MMT) | H7: =(C7-D7)/C7 -> 0.44208427
A8: Q3 FY26 | B8: Ports & Logistics | C8: 4568.7 | D8: 2482.9 | E8: 4390.7 | F8: 99 | G8: Cargo Volume (MMT) | H8: =(C8-D8)/C8 -> 0.45654125
A9: Q4 FY26 | B9: Ports & Logistics | C9: 4868.7 | D9: 2698 | E9: 4981.8 | F9: 108.9 | G9: Cargo Volume (MMT) | H9: =(C9-D9)/C9 -> 0.44584797
A10: Q1 FY25 | B10: Power | C10: 4957.8 | D10: 3465.1 | E10: 4997.9 | F10: 3110.5 | G10: Generation (MW) | H10: =(C10-D10)/C10 -> 0.30108112
A11: Q2 FY25 | B11: Power | C11: 5331.3 | D11: 3650.6 | E11: 5483.9 | F11: 3290.5 | G11: Generation (MW) | H11: =(C11-D11)/C11 -> 0.31525144
A12: Q3 FY25 | B12: Power | C12: 5162.2 | D12: 3416.5 | E12: 5090.6 | F12: 3172.8 | G12: Generation (MW) | H12: =(C12-D12)/C12 -> 0.33816977
A13: Q4 FY25 | B13: Power | C13: 5298.7 | D13: 3546.5 | E13: 5370.9 | F13: 3380.4 | G13: Generation (MW) | H13: =(C13-D13)/C13 -> 0.33068488
... A33: Q4 FY26 | B33: Cement | C33: 3327 | D33: 2372 | E33: 3366.5 | F33: 20.3 | G33: Sales Volume (MnT) | H33: =(C33-D33)/C33 -> 0.28704539
